ImgTextClipboard
